apyori.py
myapriori.py
setup.cfg
setup.py
version.py
myapriori.egg-info/PKG-INFO
myapriori.egg-info/SOURCES.txt
myapriori.egg-info/dependency_links.txt
myapriori.egg-info/entry_points.txt
myapriori.egg-info/requires.txt
myapriori.egg-info/top_level.txt