Metadata-Version: 1.1
Name: myapriori
Version: 0.0.22
Summary: Simple Apriori algorithm Implementation.
Home-page: https://github.com/jimmybow/myapriori
Author: jimmybow
Author-email: jimmybow@hotmail.com.tw
License: MIT
Platform: UNKNOWN
Classifier: License :: OSI Approved :: MIT License
Classifier: Programming Language :: Python
Classifier: Programming Language :: Python :: 2.7
Classifier: Programming Language :: Python :: 3.3
Classifier: Programming Language :: Python :: 3.4
Classifier: Programming Language :: Python :: 3.5
Classifier: Programming Language :: Python :: 3.6
Classifier: Topic :: Scientific/Engineering :: Mathematics
Classifier: Topic :: Software Development :: Libraries
Classifier: Topic :: Software Development :: Libraries :: Python Modules
